b2access.py
social_auth_backend_b2access-1.0.0.dist-info/RECORD
social_auth_backend_b2access-1.0.0.dist-info/top_level.txt
social_auth_backend_b2access-1.0.0.dist-info/DESCRIPTION.rst
social_auth_backend_b2access-1.0.0.dist-info/WHEEL
social_auth_backend_b2access-1.0.0.dist-info/metadata.json
social_auth_backend_b2access-1.0.0.dist-info/METADATA
