Metadata-Version: 2.0
Name: social-auth-backend-b2access
Version: 1.0.0
Summary: A plugin for social-auth to authenticate with b2access
Home-page: https://github.com/UNINETT/python-b2access-auth
Author: Hanne Moa
Author-email: hanne.moa@uninett.no
License: MIT
Keywords: django,oauth2
Platform: any
Classifier: Environment :: Web Environment
Classifier: Intended Audience :: Developers
Classifier: License :: OSI Approved :: MIT License
Classifier: Operating System :: OS Independent
Classifier: Programming Language :: Python
Classifier: Programming Language :: Python :: 3 :: Only
Classifier: Programming Language :: Python :: 3.4
Classifier: Programming Language :: Python :: 3.5
Classifier: Programming Language :: Python :: 3.6
Classifier: Framework :: Django
Classifier: Framework :: Django :: 1.11
Classifier: Framework :: Flask
Classifier: Framework :: Pyramid
Classifier: Topic :: Internet :: WWW/HTTP
Classifier: Topic :: Software Development :: Libraries :: Python Modules
Classifier: Topic :: Utilities
Requires-Dist: social-auth-core
